synod/__init__.py
synod/__main__.py
synod/cli.py
synod/core/__init__.py
synod/core/alt_buffer.py
synod/core/archives.py
synod/core/auto_context.py
synod/core/chat_interface.py
synod/core/checkpoints.py
synod/core/cloud_debate.py
synod/core/code_search.py
synod/core/context.py
synod/core/context_suggestions.py
synod/core/custom_commands.py
synod/core/display.py
synod/core/git_commands.py
synod/core/hooks.py
synod/core/indexer.py
synod/core/memory_viz.py
synod/core/project_context.py
synod/core/session.py
synod/core/slash_commands.py
synod/core/storage.py
synod/core/syntax.py
synod/core/test_runner.py
synod/core/theme.py
synod/core/voice.py
synod/core/workspace.py
synod/tools/__init__.py
synod/tools/base.py
synod/tools/bash.py
synod/tools/executor.py
synod/tools/file_editor.py
synod/tools/search.py
synod_cli-2.6.1.dist-info/METADATA
synod_cli-2.6.1.dist-info/WHEEL
synod_cli-2.6.1.dist-info/entry_points.txt
synod_cli-2.6.1.dist-info/licenses/LICENSE
synod_cli-2.6.1.dist-info/RECORD
