Metadata-Version: 2.4
Name: synod-cli
Version: 2.6.1
Summary: AI coding agent with adversarial debate. Multiple models critique each other, only battle-tested answers survive. Infinite memory that never forgets.
Project-URL: Homepage, https://github.com/KekwanuLabs/synod-cli
Project-URL: Documentation, https://github.com/KekwanuLabs/synod-cli/blob/main/README.md
Project-URL: Repository, https://github.com/KekwanuLabs/synod-cli
Project-URL: Issues, https://github.com/KekwanuLabs/synod-cli/issues
Author-email: KekwanuLabs <hello@kekwanu.com>
License: MIT
License-File: LICENSE
Keywords: adversarial-debate,ai,claude,cli,code-review,coding-agent,coding-assistant,gemini,gpt,llm,memory,multi-model
Classifier: Development Status :: 4 - Beta
Classifier: Intended Audience :: Developers
Classifier: License :: OSI Approved :: MIT License
Classifier: Programming Language :: Python :: 3
Classifier: Programming Language :: Python :: 3.8
Classifier: Programming Language :: Python :: 3.9
Classifier: Programming Language :: Python :: 3.10
Classifier: Programming Language :: Python :: 3.11
Classifier: Programming Language :: Python :: 3.12
Classifier: Topic :: Software Development :: Code Generators
Classifier: Topic :: Software Development :: Quality Assurance
Requires-Python: >=3.8
Requires-Dist: httpx>=0.27.0
Requires-Dist: inquirer>=3.1.0
Requires-Dist: prompt-toolkit>=3.0.43
Requires-Dist: pydantic>=2.9.0
Requires-Dist: python-dotenv>=1.0.0
Requires-Dist: pyyaml>=6.0.0
Requires-Dist: questionary>=2.0.0
Requires-Dist: rich>=13.7.1
Requires-Dist: typer>=0.12.3
Provides-Extra: dev
Requires-Dist: coverage[toml]>=7.4.0; extra == 'dev'
Requires-Dist: pytest-asyncio>=0.23.0; extra == 'dev'
Requires-Dist: pytest-cov>=4.1.0; extra == 'dev'
Requires-Dist: pytest-mock>=3.12.0; extra == 'dev'
Requires-Dist: pytest>=8.0.0; extra == 'dev'
Requires-Dist: respx>=0.21.0; extra == 'dev'
Provides-Extra: voice
Requires-Dist: faster-whisper>=1.0.0; extra == 'voice'
Requires-Dist: numpy>=1.24.0; extra == 'voice'
Requires-Dist: sounddevice>=0.4.6; extra == 'voice'
